ipih/__init__.py
ipih-1.54.dist-info/METADATA
ipih-1.54.dist-info/WHEEL
ipih-1.54.dist-info/top_level.txt
ipih-1.54.dist-info/RECORD
