Metadata-Version: 2.1
Name: ipih
Version: 1.54
Summary: Smart import for PIH module
Home-page: https://pacifichosp.com/
Author: Nikita Karachentsev
Author-email: it@pacifichosp.com
License: MIT
Requires-Dist: prettytable
Requires-Dist: colorama
Requires-Dist: grpcio
Requires-Dist: protobuf
Requires-Dist: requests
Requires-Dist: transliterate
Requires-Dist: psutil
Requires-Dist: setuptools
